flatfile/__init__.py
flatfile/accounts/__init__.py
flatfile/accounts/client.py
flatfile/accounts/types/__init__.py
flatfile/accounts/types/account.py
flatfile/accounts/types/account_patch.py
flatfile/accounts/types/account_response.py
flatfile/actions/__init__.py
flatfile/actions/client.py
flatfile/actions/types/__init__.py
flatfile/actions/types/api_action_configs.py
flatfile/actions/types/api_action_response.py
flatfile/actions/types/api_actions_response.py
flatfile/agent_exports/__init__.py
flatfile/agent_exports/client.py
flatfile/agent_exports/types/__init__.py
flatfile/agent_exports/types/agent_export.py
flatfile/agent_exports/types/agent_export_type.py
flatfile/agent_exports/types/get_agent_export_response.py
flatfile/agent_exports/types/list_agent_exports_response.py
flatfile/agents/__init__.py
flatfile/agents/client.py
flatfile/agents/types/__init__.py
flatfile/agents/types/agent.py
flatfile/agents/types/agent_config.py
flatfile/agents/types/agent_log.py
flatfile/agents/types/agent_response.py
flatfile/agents/types/agent_version.py
flatfile/agents/types/agent_version_response.py
flatfile/agents/types/compiler.py
flatfile/agents/types/detailed_agent_log.py
flatfile/agents/types/execution.py
flatfile/agents/types/get_agent_logs_response.py
flatfile/agents/types/get_detailed_agent_log_response.py
flatfile/agents/types/get_detailed_agent_logs_response.py
flatfile/agents/types/get_executions_response.py
flatfile/agents/types/list_agent_versions_response.py
flatfile/agents/types/list_agents_response.py
flatfile/apps/__init__.py
flatfile/apps/client.py
flatfile/apps/types/__init__.py
flatfile/apps/types/app.py
flatfile/apps/types/app_create.py
flatfile/apps/types/app_patch.py
flatfile/apps/types/app_response.py
flatfile/apps/types/app_type.py
flatfile/apps/types/apps_response.py
flatfile/apps/types/constraint_create.py
flatfile/apps/types/constraint_resource.py
flatfile/apps/types/constraint_response.py
flatfile/apps/types/constraint_update.py
flatfile-1.0.0.dist-info/METADATA
flatfile-1.0.0.dist-info/WHEEL
flatfile-1.0.0.dist-info/RECORD
